pwman/__init__.py
pwman/_version.py
pwman/data/__init__.py
pwman/data/convertdb.py
pwman/data/database.py
pwman/data/factory.py
pwman/data/nodes.py
pwman/data/drivers/__init__.py
pwman/data/drivers/mongodb.py
pwman/data/drivers/mysql.py
pwman/data/drivers/postgresql.py
pwman/data/drivers/sqlite.py
pwman/exchange/__init__.py
pwman/exchange/importer.py
pwman/ui/__init__.py
pwman/ui/baseui.py
pwman/ui/cli.py
pwman/ui/mac.py
pwman/ui/tools.py
pwman/ui/win.py
pwman/util/__init__.py
pwman/util/callback.py
pwman/util/config.py
pwman/util/crypto_engine.py
pwman3-0.13.1.dist-info/METADATA
pwman3-0.13.1.dist-info/WHEEL
pwman3-0.13.1.dist-info/entry_points.txt
pwman3-0.13.1.dist-info/top_level.txt
pwman3-0.13.1.dist-info/RECORD
