Metadata-Version: 2.1
Name: pwman3
Version: 0.13.1
Summary: a command line password manager with support for multiple databases.
Author-email: Oz N Tiram <oz.tiram@gmail.com>
License: GNU GPL
Project-URL: homepage, http://pwman3.github.io/pwman3/
Project-URL: documentation, https://pwman3.readthedocs.io/en/latest/
Keywords: password-manager,crypto,cli
Classifier: Environment :: Console
Classifier: Intended Audience :: End Users/Desktop
Classifier: Intended Audience :: Developers
Classifier: Intended Audience :: System Administrators
Classifier: License :: OSI Approved :: GNU General Public License v3 or later (GPLv3+)
Classifier: Operating System :: OS Independent
Classifier: Programming Language :: Python
Classifier: Programming Language :: Python :: 3
Classifier: Programming Language :: Python :: 3.9
Classifier: Programming Language :: Python :: 3.10
Classifier: Programming Language :: Python :: 3.11
Classifier: Programming Language :: Python :: 3.12
Requires-Dist: cryptography
Requires-Dist: colorama
Requires-Dist: pyreadline ; platform_system == "Windows"
